oxbow-0.4.2.dist-info/METADATA
oxbow-0.4.2.dist-info/WHEEL
oxbow/__init__.py
oxbow/_core/alignment.py
oxbow/_core/base.py
oxbow/_core/bbi.py
oxbow/_core/bed.py
oxbow/_core/gxf.py
oxbow/_core/sequence.py
oxbow/_core/variant.py
oxbow/_filetypes.py
oxbow/_pyarrow.py
oxbow/arrow.py
oxbow/core.py
oxbow/oxbow.abi3.so
oxbow/py.typed
oxbow-0.4.2.dist-info/RECORD
